coxbuild/__init__.py
coxbuild/__main__.py
coxbuild/configuration.py
coxbuild/exceptions.py
coxbuild/hooks.py
coxbuild/invocation.py
coxbuild/managers.py
coxbuild/pipelines.py
coxbuild/runners.py
coxbuild/runtime.py
coxbuild/schema.py
coxbuild/services.py
coxbuild/tasks.py
coxbuild/configurations/__init__.py
coxbuild/configurations/builders.py
coxbuild/events/__init__.py
coxbuild/events/datetime.py
coxbuild/events/filesystems.py
coxbuild/extensions/__init__.py
coxbuild/extensions/gallery.py
coxbuild/extensions/loader.py
coxbuild/extensions/builtin/__init__.py
coxbuild/extensions/dotnet/__init__.py
coxbuild/extensions/git/__init__.py
coxbuild/extensions/gradle/__init__.py
coxbuild/extensions/nodejs/__init__.py
coxbuild/extensions/python/__init__.py
coxbuild/extensions/python/docs.py
coxbuild/extensions/python/format.py
coxbuild/extensions/python/package.py
coxbuild/extensions/python/test.py
coxbuild/extensions/shell/__init__.py
coxbuild-0.1.6.dist-info/METADATA
coxbuild-0.1.6.dist-info/WHEEL
coxbuild-0.1.6.dist-info/entry_points.txt
coxbuild-0.1.6.dist-info/top_level.txt
coxbuild-0.1.6.dist-info/RECORD
