Metadata-Version: 2.1
Name: coxbuild
Version: 0.1.6
Summary: A tiny build automation tool.
Home-page: https://github.com/StardustDL/coxbuild
Author: StardustDL
Author-email: stardustdl@163.com
License: UNKNOWN
Project-URL: Source Code, https://github.com/StardustDL/coxbuild
Project-URL: Changes, https://github.com/StardustDL/coxbuild/releases
Project-URL: Documentation, https://stardustdl.github.io/coxbuild/
Project-URL: References, https://stardustdl.github.io/coxbuild/api/
Project-URL: Bug Tracker, https://github.com/StardustDL/coxbuild/issues
Platform: UNKNOWN
Classifier: License :: OSI Approved :: Mozilla Public License 2.0 (MPL 2.0)
Classifier: Operating System :: OS Independent
Classifier: Programming Language :: Python :: 3
Classifier: Programming Language :: Python :: 3.10
Classifier: Programming Language :: Python :: Implementation :: CPython
Classifier: Topic :: Utilities
Classifier: Topic :: Software Development :: Build Tools
Requires-Python: >=3.10
Requires-Dist: click (>=8.0.3)
Requires-Dist: pyyaml (>=6.0)
